{
  "title": "Russia Ke Pahadon Mein 9 Log Bin Kapdon Ke Froze... | RAAZ FILES",
  "description": "dyatlov pass incident: russia ke pahaado mein 9 trekkers ki rahasya-mayi maut - Dyatlov Pass Incident (1959) is one of Russia's most terrifying mysteries where 9 experienced hikers died mysteriously on Dead Mountain (Kholat Syakhl). In this video of RAAZ FILES, we decode the complete timeline, forensic reports, strange theories, and the 2021 scientific breakthrough that solved this case.\n\nIs video mein: Dyatlov Pass Incident: Russia Ke Pahaado Mein 9 Trekkers Ki Rahasya-mayi Maut se judi unsolved mystery, real story aur mind-blowing facts -- poori kahani Hinglish mein, RAAZ FILES par.\n\nChapters:\n00:00 Minus Thirtydegree Ki Kaddak\n01:50 Mansi Tribe Ke Local\n03:35 Minus Thirty Degree Celsius\n05:30 Chokane Wali Baat Yeh\n07:02 Maana Jata Hai Ki\n\nAise aur raaz, rahasya aur sacchi kahaniyon ke liye channel ko SUBSCRIBE karo aur bell icon dabao.\n\nAgar aapko Dyatlov Pass ki yeh true scientifically solved mystery pasand aayi, toh video ko LIKE karein aur RAAZ FILES ko SUBSCRIBE karke bell icon zaroor dabayein. Agli video mein hum baat karenge Bermuda Triangle ke us ship ki jiske 50 saal baad achanak wapas lautne ka daawa kiya jata hai!\nNaye raaz roz -- Subscribe karo. RAAZ KHULEGA.\n\nYe video entertainment aur educational purpose ke liye hai; kuch theories unverified hain / kaha jata hai.\n\n#DyatlovPassIncidentRussiaKePahaadoMein9TrekkersKiRahasyamayiMaut #RaazFiles #UnsolvedMystery #Hinglish #Mystery #Facts #Hindi #Story #Rahasya #RealStory #Documentary #Mysteries",
  "tags": [
    "dyatlov pass incident",
    "dyatlov pass mysterious deaths",
    "raaz files",
    "kholat syakhl mystery",
    "russia unsolved mysteries",
    "true horror story hinglish",
    "dyatlov pass solved science",
    "igor dyatlov",
    "slab avalanche dyatlov",
    "hindi mystery thriller",
    "unexplained mysteries",
    "mystery documentaries hindi",
    "skelton mountain story",
    "creepy historical events",
    "real mystery stories",
    "dyatlov",
    "pass",
    "incident",
    "russia",
    "pahaado",
    "mein",
    "trekkers",
    "rahasyamayi",
    "maut",
    "dyatlov facts",
    "pass facts",
    "incident facts"
  ],
  "categoryId": "22",
  "privacyStatus": "public",
  "defaultLanguage": "hi",
  "madeForKids": false
}